dji_thermal_sdk/__init__.py
dji_thermal_sdk/_nbdev.py
dji_thermal_sdk/dji_sdk.py
dji_thermal_sdk/utility.py
dji_thermal_sdk-1.3.20220517.dist-info/LICENSE
dji_thermal_sdk-1.3.20220517.dist-info/METADATA
dji_thermal_sdk-1.3.20220517.dist-info/WHEEL
dji_thermal_sdk-1.3.20220517.dist-info/entry_points.txt
dji_thermal_sdk-1.3.20220517.dist-info/top_level.txt
dji_thermal_sdk-1.3.20220517.dist-info/RECORD
