Metadata-Version: 2.1
Name: dji-thermal-sdk
Version: 1.3.20220517
Summary: use ctypes to invoke the DJI thermal SDK to process images.
Home-page: https://github.com/lyuhaitao/dji_thermal_sdk/tree/master/
Author: Haitao Lyu
Author-email: hxl170008@utdallas.edu
License: Apache Software License 2.0
Keywords: dji thermal sdk
Platform: UNKNOWN
Classifier: Development Status :: 3 - Alpha
Classifier: Intended Audience :: Developers
Classifier: Natural Language :: English
Classifier: Programming Language :: Python :: 3.6
Classifier: Programming Language :: Python :: 3.7
Classifier: Programming Language :: Python :: 3.8
Classifier: Programming Language :: Python :: 3.9
Classifier: Programming Language :: Python :: 3.10
Classifier: License :: OSI Approved :: Apache Software License
Requires-Python: >=3.6
License-File: LICENSE
Requires-Dist: pip
Requires-Dist: packaging
Provides-Extra: dev
